LICENSE
README.rst
setup.py
./LICENSE
./README.rst
./SRAdownload.py
./__init__.py
SRAdownload.egg-info/PKG-INFO
SRAdownload.egg-info/SOURCES.txt
SRAdownload.egg-info/dependency_links.txt
SRAdownload.egg-info/entry_points.txt
SRAdownload.egg-info/requires.txt
SRAdownload.egg-info/top_level.txt