Metadata-Version: 2.1
Name: SRAdownload
Version: 2.4
Summary: downloads SRA short reads from either NCBI or EBI and converts them into fastq.gz files
Home-page: https://github.com/zheminzhou/SRAdownload
Author: Zhemin Zhou
Author-email: zhemin.zhou@warwick.ac.uk
License: UNKNOWN
Keywords: bioinformatics,genomics,short reads,SRA
Platform: UNKNOWN
Classifier: Development Status :: 5 - Production/Stable
Classifier: Programming Language :: Python :: 2.7
Classifier: Programming Language :: Python :: 3.5
Classifier: Programming Language :: Python :: 3.6
Classifier: Programming Language :: Python :: 3.7
Classifier: Programming Language :: Python :: 3.8
Classifier: License :: OSI Approved :: GNU General Public License v3 (GPLv3)
Classifier: Operating System :: OS Independent
License-File: LICENSE
